MANIFEST.in
setup.py
docs/source/api.rst
docs/source/basic.rst
docs/source/conf.py
docs/source/django.rst
docs/source/examples.rst
docs/source/index.rst
docs/source/postgresql.rst
docs/source/technical.rst
json_schema_toolkit/__init__.py
json_schema_toolkit.egg-info/PKG-INFO
json_schema_toolkit.egg-info/SOURCES.txt
json_schema_toolkit.egg-info/dependency_links.txt
json_schema_toolkit.egg-info/requires.txt
json_schema_toolkit.egg-info/top_level.txt
json_schema_toolkit.egg-info/zip-safe
json_schema_toolkit/django/__init__.py
json_schema_toolkit/django/postgres/__init__.py
json_schema_toolkit/document/__init__.py
tests/__init__.py
tests/test_document.py