Metadata-Version: 1.1
Name: json-schema-toolkit
Version: 1.0a1
Summary: JSON Schema Toolkit
Home-page: http://www.petrounias.org/software/json-schema-toolkit/
Author: Alexis Petrounias <www.petrounias.org>
Author-email: UNKNOWN
License: BSD
Download-URL: https://github.com/petrounias/json-schema-toolkit/archive/master.zip
Keywords: json,schema,validation,django,sql,postgresql
Platform: UNKNOWN
Classifier: Development Status :: 3 - Alpha
Classifier: Intended Audience :: Developers
Classifier: License :: OSI Approved :: BSD License
Classifier: Operating System :: OS Independent
Classifier: Programming Language :: Python :: 2.6
Classifier: Programming Language :: Python :: 2.7
Classifier: Topic :: Software Development :: Libraries :: Python Modules
